README.txt
setup.py
docs/HISTORY.txt
redturtle/__init__.py
redturtle.maps.portlet.egg-info/PKG-INFO
redturtle.maps.portlet.egg-info/SOURCES.txt
redturtle.maps.portlet.egg-info/dependency_links.txt
redturtle.maps.portlet.egg-info/entry_points.txt
redturtle.maps.portlet.egg-info/namespace_packages.txt
redturtle.maps.portlet.egg-info/not-zip-safe
redturtle.maps.portlet.egg-info/requires.txt
redturtle.maps.portlet.egg-info/top_level.txt
redturtle/maps/__init__.py
redturtle/maps/portlet/__init__.py
redturtle/maps/portlet/adapters.py
redturtle/maps/portlet/configure.zcml
redturtle/maps/portlet/redturtlemapsportlet.pt
redturtle/maps/portlet/redturtlemapsportlet.py
redturtle/maps/portlet/version.txt
redturtle/maps/portlet/browser/__init__.py
redturtle/maps/portlet/browser/map.py
redturtle/maps/portlet/profiles/default/metadata.xml
redturtle/maps/portlet/profiles/default/portlets.xml