Metadata-Version: 1.0
Name: redturtle.maps.portlet
Version: 0.0.1
Summary: Portlet for maps.core
Home-page: http://www.redturtle.it
Author: Andrew Mleczko
Author-email: info@redturtle.it
License: GPL
Keywords: google maps plone portlet
Platform: UNKNOWN
Classifier: Framework :: Plone
Classifier: Programming Language :: Python
Classifier: Topic :: Software Development :: Libraries :: Python Modules
